hatch_msgfmt/__init__.py
hatch_msgfmt/hooks.py
hatch_msgfmt/plugin.py
hatch_msgfmt/py.typed
hatch_msgfmt/tempfile.py
hatch_msgfmt-1.1.6.dist-info/entry_points.txt
hatch_msgfmt-1.1.6.dist-info/LICENSE
hatch_msgfmt-1.1.6.dist-info/WHEEL
hatch_msgfmt-1.1.6.dist-info/METADATA
hatch_msgfmt-1.1.6.dist-info/RECORD
