Metadata-Version: 2.1
Name: hatch-msgfmt
Version: 1.1.6
Summary: Msgfmt build hook, replacing all po with mo in build
Author-email: "Taylor C. Richberger" <tcr@absolute-performance.com>
Maintainer-email: "Taylor C. Richberger" <tcr@absolute-performance.com>
Requires-Python: >=3.7
Classifier: Development Status :: 5 - Production/Stable
Classifier: Programming Language :: Python :: 3
Classifier: Framework :: Hatch
Requires-Dist: hatchling
Project-URL: repository, https://github.com/absperf/hatch-msgfmt
